AUTHORS
Changelog
INSTALL
LICENSE
MANIFEST.in
README
TODO
setup.cfg
setup.py
docs/Makefile
docs/changelog.rst
docs/conf.py
docs/index.rst
docs/introduction.rst
docs/_ext/applyxrefs.py
docs/_ext/literals_to_xrefs.py
docs/_theme/nature/theme.conf
docs/_theme/nature/static/nature.css_t
docs/_theme/nature/static/pygments.css
ghettoq/.__init__.py.swp
ghettoq/.messaging.py.swp
ghettoq/.taproot.py.swp
ghettoq/__init__.py
ghettoq/__init__.pyc
ghettoq/managers.py
ghettoq/managers.pyc
ghettoq/messaging.py
ghettoq/messaging.pyc
ghettoq/models.py
ghettoq/models.pyc
ghettoq/simple.py
ghettoq/simple.pyc
ghettoq/taproot.py
ghettoq/taproot.pyc
ghettoq.egg-info/PKG-INFO
ghettoq.egg-info/SOURCES.txt
ghettoq.egg-info/dependency_links.txt
ghettoq.egg-info/not-zip-safe
ghettoq.egg-info/top_level.txt
ghettoq/backends/.pyredis.py.swp
ghettoq/backends/__init__.py
ghettoq/backends/__init__.pyc
ghettoq/backends/base.py
ghettoq/backends/base.pyc
ghettoq/backends/beanstalk.py
ghettoq/backends/database.py
ghettoq/backends/database.pyc
ghettoq/backends/mongodb.py
ghettoq/backends/mongodb.pyc
ghettoq/backends/pyredis.py
ghettoq/backends/pyredis.pyc
ghettoq/tests/__init__.py
ghettoq/tests/__init__.pyc
ghettoq/tests/runners.py
ghettoq/tests/runners.pyc
ghettoq/tests/test_beanstalk.py
ghettoq/tests/test_database.py
ghettoq/tests/test_database.pyc
ghettoq/tests/test_mongodb.py
ghettoq/tests/test_mongodb.pyc
ghettoq/tests/test_redis.py
ghettoq/tests/test_redis.pyc