Metadata-Version: 1.0
Name: ghettoq
Version: 0.4.4
Summary: Ghetto Queue using Redis or Django Models.
Home-page: http://github.com/ask/ghettoq/
Author: Ask Solem
Author-email: askh@opera.com
License: BSD
Platform: any
Classifier: Development Status :: 4 - Beta
Classifier: Operating System :: OS Independent
Classifier: Programming Language :: Python
Classifier: Intended Audience :: Developers
Classifier: Topic :: Software Development :: Libraries :: Python Modules
